plain_rougel/__init__.py
plain_rougel/rougel.py
plain_rougel-0.1.0.dist-info/LICENSE
plain_rougel-0.1.0.dist-info/METADATA
plain_rougel-0.1.0.dist-info/WHEEL
plain_rougel-0.1.0.dist-info/top_level.txt
plain_rougel-0.1.0.dist-info/RECORD
