Metadata-Version: 2.1
Name: plain_rougel
Version: 0.1.0
Summary: A fast and multiprocessing-enabled ROUGE-L scorer.
Author-email: Igor Kilbas <whitemarsstudios@gmail.com>
Maintainer-email: Igor Kilbas <whitemarsstudios@gmail.com>
License: Copyright 2024 Igor Kilbas
Project-URL: Homepage, https://github.com/oKatanaaa/Plain-ROUGE-L
Project-URL: Repository, https://github.com/oKatanaaa/Plain-ROUGE-L
Classifier: Development Status :: 4 - Beta
Classifier: Intended Audience :: Developers
Classifier: License :: OSI Approved :: Apache Software License
Classifier: Programming Language :: Python :: 3
Classifier: Programming Language :: Python :: 3.6
Classifier: Programming Language :: Python :: 3.7
Classifier: Programming Language :: Python :: 3.8
Classifier: Programming Language :: Python :: 3.9
Classifier: Operating System :: OS Independent
Requires-Python: >=3.6
License-File: LICENSE
